<?xml version="1.0" encoding="UTF-8"?>
<treebank xmlns:saxon="http://saxon.sf.net/"
          xml:lang="grc"
          format="aldt"
          direction="ltr"
          version="1.5">
   <date>2016-10-26 12:34:49 +0000</date>
   <annotator>
      <short/>
      <name/>
      <address/>
      <uri>https://services2.perseids.org/llt/segtok</uri>
  </annotator>
   <annotator>
      <short>LauriMarjamäki</short>
      <name>Lauri Marjamäki</name>
      <address>marjamakilauri@gmail.com</address>
      <uri>http://data.perseus.org/sosol/users/LauriMarjam%C3%A4ki</uri>
  </annotator>
   <sentence document_id="https://sematia.hum.helsinki.fi/edit/442" id="1" span="" subdoc="">
      <word form="Μάξιμος" head="9" id="1" lemma="Μάξιμος" postag="n-s---mn-" relation="SBJ" />
      <word form="Σεραπειάδει" head="9" id="2" lemma="Σαραπιάς" postag="n-s---fd-" relation="OBJ" />
      <word form="τῇ" head="4" id="3" lemma="ὁ" postag="l-s---fd-" relation="ATR" />
      <word form="ἀδελφῇ" head="2" id="4" lemma="ἀδελφή" postag="n-s---fd-" relation="ATR" />
      <word form="κυρίᾳ" head="2" id="5" lemma="κυρία" postag="n-s---fd-" relation="ATR" />
      <word form="πλεῖστα" head="9" id="6" lemma="πλεῖστος" postag="a-p---na-" relation="ADV" />
      <word form="χαίρειν" head="9" id="7" lemma="χαίρω" postag="v--pna---" relation="OBJ" />
      <word form="." head="0" id="8" lemma="punc1" postag="u--------" relation="AuxK" />
      <word artificial="elliptic" form="[0]" head="0" id="9" insertion_id="0007e" relation="PRED" />
   </sentence>
   <sentence document_id="https://sematia.hum.helsinki.fi/edit/442" id="2" span="" subdoc="">
      <word form="οἶδα" head="0" id="1" lemma="οἶδα" postag="v1sria---" relation="PRED" />
      <word form="εμετὸν" head="1" id="2" lemma="ἐμαυτοῦ" postag="p-s---ma-" relation="OBJ" />
      <word form="ὅτει" head="1" id="3" lemma="ὅτι" postag="c--------" relation="AuxC" />
      <word form="οὐδὲν" head="5" id="4" lemma="οὐδείς" postag="p-s---na-" relation="ATR" />
      <word form="κακόν" head="7" id="5" lemma="κακός" postag="a-s---na-" relation="OBJ" />
      <word form="σοι" head="7" id="6" lemma="σύ" postag="p2s----d-" relation="OBJ" />
      <word form="ἐποίησα" head="8" id="7" lemma="ποιέω" postag="v1saia---" relation="OBJ_CO" />
      <word form="οὐδὲ" head="3" id="8" lemma="οὐδέ" postag="d--------" relation="COORD" />
      <word form="ἐμείσησα" head="8" id="9" lemma="μισέω" postag="v1saia---" relation="OBJ_CO" />
      <word form="ἅ" head="13" id="10" lemma="ὅς" postag="p-p---na-" relation="OBJ" />
      <word form="μοι" head="13" id="11" lemma="ἐγώ" postag="p1s---md-" relation="OBJ" />
      <word form="ταχέως" head="13" id="12" lemma="ταχέως" postag="d--------" relation="ADV" />
      <word form="ἐμείσησες" head="9" id="13" lemma="μισέω" postag="v2saia---" relation="ATR" />
      <word form="." head="0" id="14" lemma="punc1" postag="u--------" relation="AuxK" />
   </sentence>
   <sentence document_id="https://sematia.hum.helsinki.fi/edit/442" id="3" span="" subdoc="">
      <word form="οὐδὲν" head="3" id="1" lemma="οὐδείς" postag="p-s---na-" relation="ADV" />
      <word form="οὐ" head="" id="2" lemma="οὐ" postag="d--------" relation="" />
      <word form="μένφομε" head="0" id="3" lemma="μέμφομαι" postag="v1spie---" relation="PRED" />
      <word form="Οὐλέριν" head="5" id="4" lemma="Οὐαλέριος" postag="n-s---ma-" relation="ATR" />
      <word form="Λόγον" head="3" id="5" lemma="Λόγγος" postag="n-s---ma-" relation="OBJ" />
      <word form="τὸν" head="7" id="6" lemma="ὁ" postag="l-s---ma-" relation="ATR" />
      <word form="ἀδελφόν" head="5" id="7" lemma="ἀδελφός" postag="n-s---ma-" relation="ATR" />
      <word form="μου" head="7" id="8" lemma="ἐγώ" postag="p1s---mg-" relation="ATR" />
      <word form="εἰ" head="3" id="9" lemma="εἰ" postag="c--------" relation="AuxC" />
      <word form="αὐτὸς" head="12" id="10" lemma="αὐτός" postag="p-s---mn-" relation="SBJ" />
      <word form="ἠμέλησεν" head="12" id="11" lemma="ἀμελέω" postag="v3saia---" relation="ADV_CO" />
      <word form="καὶ" head="9" id="12" lemma="καί" postag="c--------" relation="COORD" />
      <word form="καταφρονεῖ" head="12" id="13" lemma="καταφρονέω" postag="v3spia---" relation="ADV_CO" />
      <word form="ἐμοῦ" head="13" id="14" lemma="ἐγώ" postag="p1s---mg-" relation="OBJ" />
      <word form="τοῦ" head="16" id="15" lemma="ὁ" postag="l-s---mg-" relation="ATR" />
      <word form="ἀδελφοῦ" head="14" id="16" lemma="ἀδελφός" postag="n-s---mg-" relation="ATR" />
      <word form="ἀτοῦ" head="16" id="17" lemma="αὐτός" postag="p-s---fg-" relation="ATR" />
      <word form="." head="0" id="18" lemma="punc1" postag="u--------" relation="AuxK" />
   </sentence>
   <sentence document_id="https://sematia.hum.helsinki.fi/edit/442" id="4" span="" subdoc="">
      <word form="σὺ" head="4" id="1" lemma="σύ" postag="p2s----n-" relation="ExD" />
      <word form="δέ" head="0" id="2" lemma="δέ" postag="d--------" relation="COORD" />
      <word form="," head="1" id="3" lemma="punc1" postag="u--------" relation="AuxX" />
      <word form="ἔδει" head="2" id="4" lemma="δέω2" postag="v3siia---" relation="PRED_CO" />
      <word form="σε" head="7" id="5" lemma="σύ" postag="p2s----a-" relation="SBJ" />
      <word form="αὐτον" head="7" id="6" lemma="αὐτός" postag="p-s---__-" relation="OBJ" />
      <word form="εἰπεῖν" head="4" id="7" lemma="εἶπον" postag="v--ana---" relation="OBJ" />
      <word form="·" head="0" id="8" lemma="punc1" postag="u--------" relation="AuxK" />
   </sentence>
   <sentence document_id="https://sematia.hum.helsinki.fi/edit/442" id="5" span="" subdoc="">
      <word form="γράψον" head="0" id="1" lemma="γράφω" postag="v2sama---" relation="PRED" />
      <word form="ὄτρακον" head="1" id="2" lemma="ὄστρακον" postag="n-s---na-" relation="OBJ" />
      <word form="τῷ" head="4" id="3" lemma="ὁ" postag="l-s---md-" relation="ATR" />
      <word form="ἀδελφῷ" head="1" id="4" lemma="ἀδελφός" postag="n-s---md-" relation="OBJ" />
      <word form="σου" head="4" id="5" lemma="σύ" postag="p2s----g-" relation="ATR" />
      <word form="." head="0" id="6" lemma="punc1" postag="u--------" relation="AuxK" />
   </sentence>
   <sentence document_id="https://sematia.hum.helsinki.fi/edit/442" id="6" span="" subdoc="">
      <word form="ἀλλὰ" head="0" id="1" lemma="ἀλλά" postag="d--------" relation="COORD" />
      <word form="οἱ" head="5" id="2" lemma="ὁ" postag="l-p---mn-" relation="SBJ" />
      <word form="παρʼ" head="2" id="3" lemma="παρά" postag="r--------" relation="AuxP" />
      <word form="ὑμεῖν" head="3" id="4" lemma="σύ" postag="p2p----d-" relation="ATR" />
      <word form="λεγείτοσαν" head="1" id="5" lemma="λέγω" postag="v3ppma---" relation="PRED_CO" />
      <word form="αποGαGις" head="" id="6" lemma="" postag="" relation="" />
   </sentence>
   <sentence document_id="https://sematia.hum.helsinki.fi/edit/442" id="7" span="" subdoc="">
      <word form="οσαν" head="" id="1" lemma="" postag="" relation="" />
      <word form="ἀπὸ" head="4" id="2" lemma="ἀπό" postag="r--------" relation="AuxP" />
      <word form="ψυχῆς" head="2" id="3" lemma="ψυχή" postag="n-s---fg-" relation="ADV" />
      <word form="εὐχαρρειστῶ" head="0" id="4" lemma="εὐχαριστέω" postag="v1spia---" relation="PRED" />
      <word form="ὑμᾶς" head="4" id="5" lemma="σύ" postag="p2p----a-" relation="OBJ" />
      <word form="." head="0" id="6" lemma="punc1" postag="u--------" relation="AuxK" />
   </sentence>
   <sentence document_id="https://sematia.hum.helsinki.fi/edit/442" id="8" span="" subdoc="">
      <word form="Παλμᾶς" head="4" id="1" lemma="Παλμᾶς" postag="n-s---mn-" relation="SBJ" />
      <word form="εἰς" head="4" id="2" lemma="εἰς" postag="r--------" relation="AuxP" />
      <word form="Καμπὴν" head="2" id="3" lemma="καμπή" postag="n-s---fa-" relation="OBJ" />
      <word form="ἀπῆλθεν" head="0" id="4" lemma="ἀπέρχομαι" postag="v3saia---" relation="PRED" />
      <word form="." head="0" id="5" lemma="punc1" postag="u--------" relation="AuxK" />
   </sentence>
   <sentence document_id="https://sematia.hum.helsinki.fi/edit/442" id="9" span="" subdoc="">
      <word form="ἡμέρας" head="2" id="1" lemma="ἡμέρα" postag="n-p---fa-" relation="OBJ" />
      <word form="ἔχι" head="0" id="2" lemma="ἔχω" postag="v3spia---" relation="PRED" />
      <word form="δ" head="1" id="3" lemma="4" postag="m-p---ma-" relation="ATR" />
      <word form="." head="0" id="4" lemma="punc1" postag="u--------" relation="AuxK" />
   </sentence>
   <sentence document_id="https://sematia.hum.helsinki.fi/edit/442" id="10" span="" subdoc="">
      <word form="περεὶ" head="4" id="1" lemma="περί" postag="r--------" relation="AuxP" />
      <word form="τοῦ" head="3" id="2" lemma="ὁ" postag="l-s---ng-" relation="ATR" />
      <word form="χοιρειδείου" head="1" id="3" lemma="χοιρίδιον" postag="n-s---ng-" relation="ADV" />
      <word form="ἀμερείμνει" head="0" id="4" lemma="ἀμεριμνέω" postag="v2spma---" relation="PRED" />
      <word form="," head="6" id="5" lemma="punc1" postag="u--------" relation="AuxX" />
      <word form="κυρεία" head="4" id="6" lemma="κυρία" postag="n-s---fv-" relation="ExD" />
      <word form="." head="0" id="7" lemma="punc1" postag="u--------" relation="AuxK" />
   </sentence>
   <sentence document_id="https://sematia.hum.helsinki.fi/edit/442" id="11" span="" subdoc="">
      <word form="ἐγὼ" head="" id="1" lemma="ἐγώ" postag="p1s---mn-" relation="" />
      <word form="πω" head="" id="2" lemma="πω" postag="d--------" relation="PRED" />
      <word form="σε" head="" id="3" lemma="σύ" postag="p2s----a-" relation="" />
      <word form="." head="0" id="4" lemma="punc1" postag="u--------" relation="AuxK" />
   </sentence>
   <sentence document_id="https://sematia.hum.helsinki.fi/edit/442" id="12" span="" subdoc="">
      <word form="πέμσον" head="0" id="1" lemma="πέμπω" postag="v2sama---" relation="PRED" />
      <word form="με" head="1" id="2" lemma="ἐγώ" postag="p1s---ma-" relation="OBJ" />
      <word form="τὸ" head="4" id="3" lemma="ὁ" postag="l-s---na-" relation="ATR" />
      <word form="πελέκειον" head="1" id="4" lemma="πελέκιον" postag="n-s---na-" relation="OBJ" />
      <word form="." head="0" id="5" lemma="punc1" postag="u--------" relation="AuxK" />
   </sentence>
   <sentence document_id="https://sematia.hum.helsinki.fi/edit/442" id="13" span="" subdoc="">
      <word form="ἄσσπασε" head="0" id="1" lemma="ἀσπάζομαι" postag="v2samm---" relation="PRED" />
      <word form="τὸν" head="3" id="2" lemma="ὁ" postag="l-s---ma-" relation="ATR" />
      <word form="ἀδελφόν" head="1" id="3" lemma="ἀδελφός" postag="n-s---ma-" relation="OBJ" />
      <word form="μου" head="3" id="4" lemma="ἐγώ" postag="p1s---mg-" relation="ATR" />
      <word form="." head="0" id="5" lemma="punc1" postag="u--------" relation="AuxK" />
   </sentence>
   <sentence document_id="https://sematia.hum.helsinki.fi/edit/442" id="14" span="" subdoc="">
      <word form="ἔρρωA" head="0" id="1" lemma="ῥώννυμι" postag="v__r__---" relation="PRED" />
      <word form="." head="0" id="2" lemma="punc1" postag="u--------" relation="AuxK" />
   </sentence>
</treebank>
