<?xml version="1.0" encoding="UTF-8"?>
<treebank xmlns:saxon="http://saxon.sf.net/"
          xml:lang="grc"
          format="aldt"
          version="1.5">
   <date>2016-01-24 18:54:57 +0000</date>
   <annotator>
      <short/>
      <name/>
      <address/>
      <uri>http://services2.perseids.org/llt/segtok</uri>
  </annotator>
   <annotator>
      <short/>
      <name/>
      <address/>
      <uri>http://github.com/latin-language-toolkit/arethusa</uri>
  </annotator>
   <annotator>
      <short>Marja Vierros</short>
      <name>Marja Vierros</name>
      <address>vierrosm@gmail.com</address>
      <uri>http://data.perseus.org/sosol/users/Marja%20Vierros</uri>
  </annotator>
   <sentence id="1"
             document_id="https://sematia.hum.helsinki.fi/edit/43"
             subdoc=""
             span="">
      <word id="1" form="πρὸς" lemma="πρός" postag="r--------" relation="AuxP" head="6"/>
      <word id="2" form="φίλους" lemma="φίλος" postag="a-p---ma-" relation="OBJ" head="1"/>
      <word id="3" form="μετὰ" lemma="μετά" postag="r--------" relation="AuxP" head="6"/>
      <word id="4" form="κολαγίας" lemma="κολακεία" postag="n-s---fg-" relation="ADV" head="3"/>
      <word id="5" form="." lemma="punc1" postag="u--------" relation="AuxK" head="0"/>
      <word id="6" insertion_id="0000e" artificial="elliptic" relation="PRED" form="[0]" head="0"/>
   </sentence>
   <sentence id="2"
             document_id="https://sematia.hum.helsinki.fi/edit/43"
             subdoc=""
             span="">
      <word id="1" form="ιϛ" lemma="16" postag="m-p---__-" relation="ADV" head="3"/>
      <word id="2" form="." lemma="punc1" postag="u--------" relation="AuxK" head="0"/>
      <word id="3" insertion_id="0001e" artificial="elliptic" relation="PRED" form="[0]" head="0"/>
   </sentence>
</treebank>
